{
  "main": {
    "id": "f0be58b2f890d605",
    "type": "split",
    "children": [
      {
        "id": "7d9aad8d2a0f3a75",
        "type": "tabs",
        "children": [
          {
            "id": "e8f3cfbb0d91659c",
            "type": "leaf",
            "state": {
              "type": "markdown",
              "state": {
                "file": "Try-rescue.md",
                "mode": "source",
                "source": false
              }
            }
          }
        ]
      }
    ],
    "direction": "vertical"
  },
  "left": {
    "id": "5294af8cb73d0337",
    "type": "split",
    "children": [
      {
        "id": "e3a5dbbe200894ce",
        "type": "tabs",
        "children": [
          {
            "id": "995f13a032b9c717",
            "type": "leaf",
            "state": {
              "type": "file-explorer",
              "state": {
                "sortOrder": "alphabetical"
              }
            }
          },
          {
            "id": "a236e42ccc14c9a1",
            "type": "leaf",
            "state": {
              "type": "search",
              "state": {
                "query": "",
                "matchingCase": true,
                "explainSearch": false,
                "collapseAll": false,
                "extraContext": false,
                "sortOrder": "alphabetical"
              }
            }
          },
          {
            "id": "df3f128571ad0d51",
            "type": "leaf",
            "state": {
              "type": "bookmarks",
              "state": {}
            }
          }
        ]
      }
    ],
    "direction": "horizontal",
    "width": 201.5
  },
  "right": {
    "id": "714229101c7e98ff",
    "type": "split",
    "children": [
      {
        "id": "5007ce681a15608f",
        "type": "tabs",
        "children": [
          {
            "id": "9ce0d7258e7f0a42",
            "type": "leaf",
            "state": {
              "type": "outgoing-link",
              "state": {
                "file": "Try-rescue.md",
                "linksCollapsed": false,
                "unlinkedCollapsed": true
              }
            }
          },
          {
            "id": "60ea54ddbe2e6242",
            "type": "leaf",
            "state": {
              "type": "tag",
              "state": {
                "sortOrder": "frequency",
                "useHierarchy": false
              }
            }
          },
          {
            "id": "dc2bdc177deead3c",
            "type": "leaf",
            "state": {
              "type": "outline",
              "state": {
                "file": "Try-rescue.md"
              }
            }
          },
          {
            "id": "179365767efcc2e6",
            "type": "leaf",
            "state": {
              "type": "all-properties",
              "state": {
                "sortOrder": "frequency",
                "showSearch": false,
                "searchQuery": ""
              }
            }
          },
          {
            "id": "6f8dff0f8a9e2e4a",
            "type": "leaf",
            "state": {
              "type": "backlink",
              "state": {
                "file": "Try-rescue.md",
                "collapseAll": false,
                "extraContext": false,
                "sortOrder": "alphabetical",
                "showSearch": false,
                "searchQuery": "",
                "backlinkCollapsed": false,
                "unlinkedCollapsed": true
              }
            }
          },
          {
            "id": "d7babed2616decdf",
            "type": "leaf",
            "state": {
              "type": "mermaid-toolbar-view",
              "state": {}
            }
          }
        ]
      }
    ],
    "direction": "horizontal",
    "width": 200,
    "collapsed": true
  },
  "left-ribbon": {
    "hiddenItems": {
      "canvas:Crear nuevo lienzo": false,
      "switcher:Abrir selector rápido": false,
      "graph:Abrir vista gráfica": false,
      "daily-notes:Abrir la nota de hoy": false,
      "templates:Insertar plantilla": false,
      "command-palette:Abrir paleta de comandos": false,
      "obsidian42-brat:BRAT": false,
      "mermaid-tools:Open Mermaid Toolbar": false,
      "obsidian-excalidraw-plugin:Create new drawing": false
    }
  },
  "active": "e8f3cfbb0d91659c",
  "lastOpenFiles": [
    "Q6/AS/Prácticas/Elixir.md",
    "Try-rescue.md",
    "Try/rescue.md",
    "Try",
    "Errores.md",
    "Need for speed.md",
    "Q6/AS/Prácticas/Alias.md",
    "Q6/AS/Prácticas/Import.md",
    "Excalidraw/Diagrama relacional ejercicio 1.md",
    "Excalidraw/Drawing 2024-03-03 23.43.48.excalidraw.md",
    "Q6/AS/Prácticas/Captain's log.md",
    "Q6/AS/Prácticas/Librerías de Erlang.md",
    "Q6/AS/Prácticas/Aleatorios.md",
    "Q6/AS/Prácticas/Bread and potions.md",
    "Q6/AS/Prácticas/Protocolos.md",
    "Q6/AS/Prácticas/Community garden.md",
    "Q6/AS/Prácticas/Agent.md",
    "Q6/AS/Tema 4/Tema 4-Arquitecturaas centradas en la comunicación.md",
    "Q6/AS/Arquitectura do software.md",
    "Q6/ER/Tema 5/Tema 5-Casos de uso.md",
    "Q6/AS/Tema 4",
    "Excalidraw/Drawing 2024-03-01 11.31.16.excalidraw.md",
    "Q6/ER/Tema 5/UML para casos de uso.md",
    "Excalidraw/Drawing 2024-03-01 11.28.38.excalidraw.md",
    "Q6/ER/Tema 1/Definiciones de ingeniería de requisitos.md",
    "Q6/ER/Tema 5/Ejemplo de casos de uso.md",
    "Q6/ER/Tema 5/Casos de uso.md",
    "Q6/ER/Tema 5/Introducción a los casos de uso.md",
    "Q6/ER/Tema 5",
    "Imágenes/rest 1 2.png",
    "Imágenes/rest 1.png",
    "Imágenes/controladores.png",
    "Q6/BDA/Seguridad",
    "Imágenes/cache de primer nivel.png",
    "Imágenes/pagina web Bellas.png",
    "Excalidraw",
    "Q6/AS/Tema 3",
    "Q6/ER/Tema 4",
    "Imágenes/ejemplo 3 jerarquia.png",
    "Imágenes/ejemplo 2 jerarquia.png",
    "Imágenes/ejemplo 1 jerarquia.png",
    "Imágenes/relacion N M.png",
    "Imágenes/relacion 1 N.png",
    "Q6/PA/Tema 4",
    "Q6/ACL/Tema 3",
    "Q6/BDA/Integridad",
    "Sin título.canvas",
    "Sin título 1.canvas"
  ]
}